Rhapso/__init__.py
Rhapso/data_prep/__init__.py
Rhapso/data_prep/n5_reader.py
Rhapso/data_prep/s3_big_stitcher_reader.py
Rhapso/data_prep/xml_to_dataframe.py
Rhapso/detection/__init__.py
Rhapso/detection/advanced_refinement.py
Rhapso/detection/difference_of_gaussian.py
Rhapso/detection/image_reader.py
Rhapso/detection/metadata_builder.py
Rhapso/detection/overlap_detection.py
Rhapso/detection/points_validation.py
Rhapso/detection/save_interest_points.py
Rhapso/detection/view_transform_models.py
Rhapso/fusion/__init__.py
Rhapso/fusion/affine_fusion_worker.py
Rhapso/fusion/multiscale_worker.py
Rhapso/fusion/neuroglancer_link_gen_worker.py
Rhapso/fusion/affine_fusion/__init__.py
Rhapso/fusion/affine_fusion/blend.py
Rhapso/fusion/affine_fusion/fusion.py
Rhapso/fusion/affine_fusion/geometry.py
Rhapso/fusion/affine_fusion/io.py
Rhapso/fusion/affine_fusion/script_utils.py
Rhapso/fusion/affine_fusion/setup.py
Rhapso/fusion/multiscale/__init__.py
Rhapso/fusion/multiscale/aind_hcr_data_transformation/__init__.py
Rhapso/fusion/multiscale/aind_hcr_data_transformation/models.py
Rhapso/fusion/multiscale/aind_hcr_data_transformation/zeiss_job.py
Rhapso/fusion/multiscale/aind_hcr_data_transformation/compress/__init__.py
Rhapso/fusion/multiscale/aind_hcr_data_transformation/compress/czi_to_zarr.py
Rhapso/fusion/multiscale/aind_hcr_data_transformation/compress/zarr_writer.py
Rhapso/fusion/multiscale/aind_hcr_data_transformation/utils/__init__.py
Rhapso/fusion/multiscale/aind_hcr_data_transformation/utils/utils.py
Rhapso/fusion/multiscale/aind_z1_radial_correction/__init__.py
Rhapso/fusion/multiscale/aind_z1_radial_correction/array_to_zarr.py
Rhapso/fusion/multiscale/aind_z1_radial_correction/radial_correction.py
Rhapso/fusion/multiscale/aind_z1_radial_correction/run_capsule.py
Rhapso/fusion/multiscale/aind_z1_radial_correction/worker.py
Rhapso/fusion/multiscale/aind_z1_radial_correction/utils/__init__.py
Rhapso/fusion/multiscale/aind_z1_radial_correction/utils/utils.py
rhapso-0.1.991.dist-info/licenses/LICENSE
rhapso-0.1.991.dist-info/METADATA
rhapso-0.1.991.dist-info/WHEEL
rhapso-0.1.991.dist-info/top_level.txt
rhapso-0.1.991.dist-info/RECORD
