Metadata-Version: 2.4
Name: Rhapso
Version: 0.1.991
Summary: A python package for aligning and stitching light sheet fluorescence microscopy images
Author: ND
Author-email: sean.fite@alleninstitute.org
Project-URL: Source, https://github.com/AllenNeuralDynamics/Rhapso
Project-URL: Roadmap, https://github.com/AllenNeuralDynamics/Rhapso/issues
Classifier: Development Status :: 3 - Alpha
Classifier: Intended Audience :: Developers
Classifier: Natural Language :: English
Classifier: Programming Language :: Python :: 3
Classifier: Programming Language :: Python :: 3.7
Classifier: Programming Language :: Python :: 3.8
Classifier: Programming Language :: Python :: 3.9
Classifier: Programming Language :: Python :: 3.10
Classifier: Operating System :: OS Independent
Requires-Python: >=3.7
License-File: LICENSE
Requires-Dist: pandas
Requires-Dist: dask[array]==2024.12.1
Requires-Dist: zarr==2.18.3
Requires-Dist: scipy==1.13.1
Requires-Dist: scikit-image
Requires-Dist: bioio==1.3.0
Requires-Dist: bioio-tifffile==1.0.0
Requires-Dist: tifffile==2025.1.10
Requires-Dist: dask-image==2024.5.3
Requires-Dist: boto3==1.35.92
Requires-Dist: numcodecs==0.13.1
Requires-Dist: matplotlib==3.10.0
Requires-Dist: memory-profiler==0.61.0
Requires-Dist: s3fs==2024.12.0
Requires-Dist: scikit-learn
Dynamic: author
Dynamic: author-email
Dynamic: classifier
Dynamic: description
Dynamic: description-content-type
Dynamic: license-file
Dynamic: project-url
Dynamic: requires-dist
Dynamic: requires-python
Dynamic: summary
